autonomous_dq_agent-0.1.0.dist-info/licenses/LICENSE
dq_agent/__init__.py
dq_agent/cli.py
dq_agent/db_connector.py
autonomous_dq_agent-0.1.0.dist-info/METADATA
autonomous_dq_agent-0.1.0.dist-info/WHEEL
autonomous_dq_agent-0.1.0.dist-info/entry_points.txt
autonomous_dq_agent-0.1.0.dist-info/top_level.txt
autonomous_dq_agent-0.1.0.dist-info/RECORD
