Metadata-Version: 2.4
Name: autonomous-dq-agent
Version: 0.1.0
Summary: A cloud-ready, ML-powered, rule-driven data quality agent.
Author: Sudheer
Classifier: Programming Language :: Python :: 3
Classifier: License :: OSI Approved :: MIT License
License-File: LICENSE
Requires-Dist: pandas
Requires-Dist: pyyaml
Requires-Dist: scikit-learn
Requires-Dist: sqlalchemy
Requires-Dist: boto3
Dynamic: author
Dynamic: classifier
Dynamic: license-file
Dynamic: requires-dist
Dynamic: summary
